tooncher/__init__.py
tooncher/_cli.py
tooncher-1.0.3.dist-info/LICENSE.txt
tooncher-1.0.3.dist-info/METADATA
tooncher-1.0.3.dist-info/WHEEL
tooncher-1.0.3.dist-info/entry_points.txt
tooncher-1.0.3.dist-info/top_level.txt
tooncher-1.0.3.dist-info/RECORD
