Metadata-Version: 2.1
Name: tooncher
Version: 1.0.3
Summary: automates toontown rewritten's login process
Home-page: https://github.com/fphammerle/tooncher
Author: Fabian Peter Hammerle
Author-email: fabian.hammerle@gmail.com
License: UNKNOWN
Keywords: game,launcher,toontown rewritten,ttr
Platform: UNKNOWN
Classifier: Development Status :: 4 - Beta
Classifier: Intended Audience :: End Users/Desktop
Classifier: License :: OSI Approved :: MIT License
Classifier: Operating System :: MacOS :: MacOS X
Classifier: Operating System :: POSIX :: Linux
Classifier: Programming Language :: Python :: 3.5
Classifier: Programming Language :: Python :: 3.6
Classifier: Programming Language :: Python :: 3.7
Classifier: Programming Language :: Python :: 3.8
Classifier: Topic :: Games/Entertainment
Classifier: Topic :: Utilities
Requires-Dist: pyyaml
